drf_bf_protect/__init__.py
drf_bf_protect/admin.py
drf_bf_protect/apps.py
drf_bf_protect/backend.py
drf_bf_protect/config.py
drf_bf_protect/decorators.py
drf_bf_protect/models.py
drf_bf_protect/migrations/0001_initial.py
drf_bf_protect/migrations/__init__.py
drf_bf_protect-0.0.2.dist-info/METADATA
drf_bf_protect-0.0.2.dist-info/WHEEL
drf_bf_protect-0.0.2.dist-info/licenses/LICENSE
drf_bf_protect-0.0.2.dist-info/RECORD
