Metadata-Version: 2.4
Name: drf-bf-protect
Version: 0.0.2
Summary: A device token driven bruteforce protection for the Django REST framework
Project-URL: Homepage, https://gitlab.com/sparrow.242.de/drf_bt_protect
Project-URL: Issues, https://gitlab.com/sparrow.242.de/drf_bt_protect/issues
Author-email: Sebastian Meyer <sparrow.242.de@gmail.com>
License-Expression: GPL-3.0
License-File: LICENSE
Classifier: Development Status :: 3 - Alpha
Classifier: License :: OSI Approved :: GNU General Public License v3 (GPLv3)
Classifier: Operating System :: OS Independent
Classifier: Programming Language :: Python :: 3
Requires-Python: >=3.6
